pyarithops/__init__.py
pyarithops-0.0.1.dist-info/LICENSE
pyarithops-0.0.1.dist-info/METADATA
pyarithops-0.0.1.dist-info/WHEEL
pyarithops-0.0.1.dist-info/top_level.txt
pyarithops-0.0.1.dist-info/RECORD
