Metadata-Version: 2.1
Name: pyarithops
Version: 0.0.1
Summary: A package for evaluation of Arithmetic operations.
Author-email: Atiq Mansoori <atiqsm24@gmail.com>
Project-URL: Homepage, https://github.com/ASM313/pyarithops
Project-URL: Bug Tracker, https://github.com/ASM313/pyarithops/issues
Classifier: Programming Language :: Python :: 3
Classifier: License :: OSI Approved :: MIT License
Classifier: Operating System :: OS Independent
Requires-Python: >=3.7
License-File: LICENSE
